Metadata-Version: 2.1
Name: revuot
Version: 0.3
Summary: a reverse shell for testing perpose
Author: hisamdavid (dawood hithem)
Author-email: <deviddevid287@gmail.com>
Keywords: python,hacking,backdoor,tojen,reverse shell,cyper security
Classifier: Development Status :: 1 - Planning
Classifier: Intended Audience :: Developers
Classifier: Programming Language :: Python :: 3
Classifier: Operating System :: Unix
Classifier: Operating System :: MacOS :: MacOS X
Classifier: Operating System :: Microsoft :: Windows
